gns3_client/__init__.py
gns3_client-0.1.0.dist-info/LICENSE.md
gns3_client-0.1.0.dist-info/WHEEL
gns3_client-0.1.0.dist-info/METADATA
gns3_client-0.1.0.dist-info/RECORD
