Metadata-Version: 2.1
Name: gns3-client
Version: 0.1.0
Summary: Python API client for GNS3 network simulation tool
Home-page: https://github.com/desnoe/gns3-client
License: MIT
Keywords: gns3
Author: Olivier Desnoe
Author-email: olivier@delarche.fr
Requires-Python: >=3.9,<4.0
Classifier: License :: OSI Approved :: MIT License
Classifier: Programming Language :: Python :: 3
Classifier: Programming Language :: Python :: 3.10
Classifier: Programming Language :: Python :: 3.9
Requires-Dist: logzero (>=1.7.0,<2.0.0)
Requires-Dist: requests (>=2.26.0,<3.0.0)
Requires-Dist: requests-cache (>=0.8.1,<0.9.0)
Requires-Dist: urllib3 (>=1.26.7,<2.0.0)
